ibkr_porez/__about__.py
ibkr_porez/__init__.py
ibkr_porez/config.py
ibkr_porez/declaration_gains_xml.py
ibkr_porez/ibkr_csv.py
ibkr_porez/ibkr_flex_query.py
ibkr_porez/main.py
ibkr_porez/models.py
ibkr_porez/nbs.py
ibkr_porez/report_gains.py
ibkr_porez/report_income.py
ibkr_porez/report_params.py
ibkr_porez/storage.py
ibkr_porez/tables.py
ibkr_porez/tax.py
ibkr_porez/validation.py
ibkr_porez-1.2.0.dist-info/METADATA
ibkr_porez-1.2.0.dist-info/WHEEL
ibkr_porez-1.2.0.dist-info/entry_points.txt
ibkr_porez-1.2.0.dist-info/licenses/LICENSE.txt
ibkr_porez-1.2.0.dist-info/RECORD
