Metadata-Version: 2.4
Name: ibkr-porez
Version: 1.2.0
Summary: Automated PPDG-3R tax reports for Interactive Brokers. It automatically pulls your data and generates a ready-to-upload XML file with all prices converted to RSD.
Project-URL: Homepage, https://andgineer.github.io/ibkr-porez/
Project-URL: Documentation, https://andgineer.github.io/ibkr-porez/
Author-email: Andrey Sorokin <andrey@sorokin.engineer>
License: Copyright (c) 2024 Andrey Sorokin <andrey@sorokin.engineer>
License-File: LICENSE.txt
Keywords: one,two
Classifier: License :: OSI Approved :: MIT License
Classifier: Operating System :: OS Independent
Classifier: Programming Language :: Python :: 3
Requires-Python: >=3.10
Requires-Dist: click>=8.2.0
Requires-Dist: holidays>=0.63
Requires-Dist: holidays>=0.89
Requires-Dist: pandas>=2.0.0
Requires-Dist: platformdirs>=4.3.6
Requires-Dist: pydantic>=2.10.6
Requires-Dist: python-dateutil>=2.8.2
Requires-Dist: requests>=2.32.3
Requires-Dist: rich-click>=1.8.8
Requires-Dist: tenacity>=9.0.0
